arena_cam_config/__init__.py
arena_cam_config/main.py
arena_cam_config-0.1.0.dist-info/LICENSE
arena_cam_config-0.1.0.dist-info/METADATA
arena_cam_config-0.1.0.dist-info/WHEEL
arena_cam_config-0.1.0.dist-info/entry_points.txt
arena_cam_config-0.1.0.dist-info/top_level.txt
arena_cam_config-0.1.0.dist-info/RECORD
