Metadata-Version: 2.1
Name: arena-cam-config
Version: 0.1.0
Summary: Camera Configuration GUI using Textual for ArenaSDK cameras
Author-email: Laurence <laurence.diack@peekrobotics.co.nz>
Maintainer-email: Laurence <laurence.diack@peekrobotics.co.nz>
License: MIT
Project-URL: Homepage, https://github.com/laurence-diack-pk/arena-cam-config
Project-URL: Documentation, https://github.com/laurence-diack-pk/arena-cam-config#readme
Project-URL: Repository, https://github.com/laurence-diack-pk/arena-cam-config.git
Project-URL: Bug Tracker, https://github.com/laurence-diack-pk/arena-cam-config/issues
Keywords: camera,configuration,gui,textual,arena,sdk
Classifier: Development Status :: 4 - Beta
Classifier: Environment :: Console
Classifier: Intended Audience :: Developers
Classifier: License :: OSI Approved :: MIT License
Classifier: Operating System :: OS Independent
Classifier: Programming Language :: Python :: 3
Classifier: Programming Language :: Python :: 3.8
Classifier: Programming Language :: Python :: 3.9
Classifier: Programming Language :: Python :: 3.10
Classifier: Programming Language :: Python :: 3.11
Classifier: Programming Language :: Python :: 3.12
Classifier: Topic :: Software Development :: User Interfaces
Classifier: Topic :: Multimedia :: Graphics :: Capture
Classifier: Topic :: Scientific/Engineering :: Image Processing
Requires-Python: >=3.8
License-File: LICENSE
Requires-Dist: textual>=0.41.0
Requires-Dist: arena-api>=2.0.0
Provides-Extra: dev
Requires-Dist: pytest>=7.0; extra == "dev"
Requires-Dist: pytest-cov; extra == "dev"
Requires-Dist: black; extra == "dev"
Requires-Dist: flake8; extra == "dev"
Requires-Dist: isort; extra == "dev"
Requires-Dist: mypy; extra == "dev"
